Ejercicio 2/datos.v
module Acumulator(input wire [3:0] D,input wire load, reset, clk, output reg[3:0] Q );

    always @(posedge clk, posedge reset) begin
        if (reset) Q = 0; 
        else if(load) begin 
            Q <= D;
        end
    end
endmodule

module ALU(input wire[3:0] A,B,input [2:0] control , output wire [3:0] out, output wire C, Z );
    reg[4:0] resultado; 
    assign Z = ~(resultado[0] | resultado[1] | resultado[2] | resultado[3]); 
    assign out = resultado[4:0]; 
    assign C = resultado[4] ;
    always @ (A,B,control) begin  
        case(control)
            3'b000: resultado <= A; 
            3'b001: resultado <= A -B;   
            3'b010: resultado <= B; 
            3'b011: resultado <= A + B;
            3'b100: resultado <= ~(A|B); 
            default: resultado <= 0; 
        endcase
    end
endmodule

module Procesamiento(input wire[3:0] dataIn,input wire[2:0] control,
                      input wire  enableOutALU, loadAcu, reset, clk, output wire[3:0] dataOut, output wire C,Z);

    wire [3:0] data; 
    wire [3:0] acuOut; 
    
    Triestate busDriverOut(data,enableOutALU,dataOut);
    Acumulator acu(data,loadAcu,reset,clk,acuOut);
    ALU aritmetica(acuOut,dataIn,control,data,C,Z);
endmodule

Ejercicio 2/Tris.v
module Triestate(input [3:0] in,input wire enable, output wire [3:0] y );
    assign y[0] = (enable ? in[0] : 1'bz );
    assign y[1] = (enable ? in[1] : 1'bz );
    assign y[2] = (enable ? in[2] : 1'bz );
    assign y[3] = (enable ? in[3] : 1'bz );
endmodule

Ejercicio 2/datos_tb.v
 module testbench();
    reg[3:0] dataIn;
    reg[2:0] control;
    reg  enableOutALU, loadAcu, reset, clk;
    wire[3:0] dataOut;
    wire C,Z;
    Procesamiento process(dataIn, control, enableOutALU, loadAcu, reset, clk, dataOut,C,Z);

    always #1 clk = ~clk;

    initial clk = 0;
    
    initial begin
        reset=0; loadAcu=0; enableOutALU=0; control=0; dataIn = 0;
        #1 reset=1;
        #1 reset=0;
        #2 dataIn=15;
        #2 enableOutALU=1;
        #2 control = 3;
        #1 loadAcu = 1;
        #1 loadAcu = 0; 
        #4  dataIn=6;
        #2  control = 1; 
        #1  loadAcu = 1;
        #1  loadAcu = 0;
        #2  control = 2; 
        #1  loadAcu  = 1;
        #1  loadAcu = 0; 
        #2  enableOutALU = 0; 
        #2  enableOutALU = 1; 
        #2  dataIn = 10;
        #1  loadAcu = 1; 
        #1  loadAcu = 0; 
        #2  control = 4; 
        #2  dataIn = 8;
        #4 $finish;
    end
    initial begin
        $dumpfile("datos_tb.vcd");
        $dumpvars(0,testbench);
    end
 endmodule

Ejercicio 2/datos_tb.vcd
$date
	Sun Nov 08 00:44:17 2020
$end
$version
	Icarus Verilog
$end
$timescale
	1ps
$end
$scope module testbench $end
$var wire 4 ! dataOut [3:0] $end
$var wire 1 " Z $end
$var wire 1 # C $end
$var reg 1 $ clk $end
$var reg 3 % control [2:0] $end
$var reg 4 & dataIn [3:0] $end
$var reg 1 ' enableOutALU $end
$var reg 1 ( loadAcu $end
$var reg 1 ) reset $end
$scope module process $end
$var wire 1 $ clk $end
$var wire 3 * control [2:0] $end
$var wire 4 + dataIn [3:0] $end
$var wire 1 ' enableOutALU $end
$var wire 1 ( loadAcu $end
$var wire 1 ) reset $end
$var wire 4 , dataOut [3:0] $end
$var wire 4 - data [3:0] $end
$var wire 4 . acuOut [3:0] $end
$var wire 1 " Z $end
$var wire 1 # C $end
$scope module acu $end
$var wire 1 $ clk $end
$var wire 1 ( load $end
$var wire 1 ) reset $end
$var wire 4 / D [3:0] $end
$var reg 4 0 Q [3:0] $end
$upscope $end
$scope module aritmetica $end
$var wire 4 1 A [3:0] $end
$var wire 4 2 B [3:0] $end
$var wire 1 " Z $end
$var wire 3 3 control [2:0] $end
$var wire 4 4 out [3:0] $end
$var wire 1 # C $end
$var reg 5 5 resultado [4:0] $end
$upscope $end
$scope module busDriverOut $end
$var wire 1 ' enable $end
$var wire 4 6 in [3:0] $end
$var wire 4 7 y [3:0] $end
$upscope $end
$upscope $end
$upscope $end
$enddefinitions $end
#0
$dumpvars
bz 7
bx 6
b0xxxx 5
bx 4
b0 3
b0 2
bx 1
bx 0
bx /
bx .
bx -
bz ,
b0 +
b0 *
0)
0(
0'
b0 &
b0 %
0$
0#
x"
bz !
$end
#1
1"
b0 -
b0 /
b0 4
b0 6
b0 5
b0 .
b0 0
b0 1
1)
1$
#2
0)
0$
#3
1$
#4
0$
b1111 &
b1111 +
b1111 2
#5
1$
#6
b0 !
b0 ,
b0 7
0$
1'
#7
1$
#8
0"
b1111 !
b1111 ,
b1111 7
b1111 -
b1111 /
b1111 4
b1111 6
b1111 5
0$
b11 %
b11 *
b11 3
#9
b1110 !
b1110 ,
b1110 7
b1110 -
b1110 /
b1110 4
b1110 6
1#
b11110 5
b1111 .
b1111 0
b1111 1
1$
1(
#10
0$
0(
#11
1$
#12
0$
#13
1$
#14
b101 !
b101 ,
b101 7
b101 -
b101 /
b101 4
b101 6
b10101 5
0$
b110 &
b110 +
b110 2
#15
1$
#16
b1001 !
b1001 ,
b1001 7
b1001 -
b1001 /
b1001 4
b1001 6
0#
b1001 5
0$
b1 %
b1 *
b1 3
#17
b11 !
b11 ,
b11 7
b11 -
b11 /
b11 4
b11 6
b11 5
b1001 .
b1001 0
b1001 1
1$
1(
#18
0$
0(
#19
1$
#20
b110 !
b110 ,
b110 7
b110 -
b110 /
b110 4
b110 6
b110 5
0$
b10 %
b10 *
b10 3
#21
b110 .
b110 0
b110 1
1$
1(
#22
0$
0(
#23
1$
#24
bz !
bz ,
bz 7
0$
0'
#25
1$
#26
b110 !
b110 ,
b110 7
0$
1'
#27
1$
#28
b1010 !
b1010 ,
b1010 7
b1010 -
b1010 /
b1010 4
b1010 6
b1010 5
0$
b1010 &
b1010 +
b1010 2
#29
b1010 .
b1010 0
b1010 1
1$
1(
#30
0$
0(
#31
1$
#32
b101 !
b101 ,
b101 7
b101 -
b101 /
b101 4
b101 6
1#
b10101 5
0$
b100 %
b100 *
b100 3
#33
1$
#34
0$
b1000 &
b1000 +
b1000 2
